awesome_commit/__init__.py
awesome_commit/__main__.py
awesome_commit/config.py
awesome_commit/editor.py
awesome_commit/git.py
awesome_commit/pre_commit.py
awesome_commit/prompts/__init__.py
awesome_commit/prompts/generate_commit_message.txt.jinja2
awesome_commit-0.1.0.dist-info/METADATA
awesome_commit-0.1.0.dist-info/WHEEL
awesome_commit-0.1.0.dist-info/entry_points.txt
awesome_commit-0.1.0.dist-info/top_level.txt
awesome_commit-0.1.0.dist-info/RECORD
