Metadata-Version: 2.4
Name: awesome-commit
Version: 0.1.0
Summary: An AI to generate great commit messages
Author-email: Jon Grace-Cox <30441316+jongracecox@users.noreply.github.com>
License: MIT
Requires-Python: >=3.8
Requires-Dist: colored
Requires-Dist: sh
Requires-Dist: loguru
Requires-Dist: questionary
Requires-Dist: python-decouple
Requires-Dist: google-genai
Requires-Dist: jinja2
